public class Second {
  public Second();
    Code:
       0: aload_0
       1: invokespecial #8                  // Method java/lang/Object."<init>":()V
       4: return

  public static void main(java.lang.String[]);
    Code:
       0: new           #12                 // class FieldsTest
       3: dup
       4: invokespecial #13                 // Method FieldsTest."<init>":()V
       7: astore_1
       8: aload_1
       9: invokespecial #16                 // Method FieldsTest.print10:()V
      12: return
}



public class Second {
  public Second();
    Code:
       0: aload_0
       1: invokespecial #1                  // Method java/lang/Object."<init>":()V
       4: return

  public static void main(java.lang.String[]);
    Code:
       0: new           #2                  // class FieldsTest
       3: dup
       4: invokespecial #3                  // Method FieldsTest."<init>":()V
       7: astore_1
       8: aload_1
       9: invokevirtual #4                  // Method FieldsTest.print10:()V
      12: return
}