public class FieldsTest {
  public FieldsTest();
    Code:
       0: aload_0
       1: invokespecial #8                  // Method java/lang/Object."<init>":()V
       4: return

  public int start(int);
    Code:
       0: getstatic     #16                 // Field java/lang/System.out:Ljava/io/PrintStream;
       3: iload_1
       4: invokevirtual #21                 // Method "Ljava/io/PrintStream;".println:(I)V
       7: iload_1
       8: ldc           #22                 // int 1
      10: iadd
      11: ireturn

  public static void main(java.lang.String[]);
    Code:
       0: aload_0
       1: ldc           #25                 // int 10
       3: invokevirtual #27                 // Method start:(I)I
       6: istore_1
       7: return
}





